odoo/addons/crm_stage_mail/README.rst
odoo/addons/crm_stage_mail/__init__.py
odoo/addons/crm_stage_mail/__manifest__.py
odoo/addons/crm_stage_mail/i18n/crm_stage_mail.pot
odoo/addons/crm_stage_mail/i18n/es.po
odoo/addons/crm_stage_mail/i18n/it.po
odoo/addons/crm_stage_mail/models/__init__.py
odoo/addons/crm_stage_mail/models/crm_lead.py
odoo/addons/crm_stage_mail/models/crm_stage.py
odoo/addons/crm_stage_mail/readme/CONTRIBUTORS.md
odoo/addons/crm_stage_mail/readme/DESCRIPTION.md
odoo/addons/crm_stage_mail/readme/USAGE.md
odoo/addons/crm_stage_mail/static/description/icon.png
odoo/addons/crm_stage_mail/static/description/index.html
odoo/addons/crm_stage_mail/tests/__init__.py
odoo/addons/crm_stage_mail/tests/test_crm_stage_mail.py
odoo/addons/crm_stage_mail/views/crm_stage_views.xml
odoo_addon_crm_stage_mail-18.0.1.0.0.4.dist-info/METADATA
odoo_addon_crm_stage_mail-18.0.1.0.0.4.dist-info/WHEEL
odoo_addon_crm_stage_mail-18.0.1.0.0.4.dist-info/top_level.txt
odoo_addon_crm_stage_mail-18.0.1.0.0.4.dist-info/RECORD
